learnblock-3.1.7.data/data/share/applications/Learnblock.desktop
learnblock-3.1.7.data/data/share/icons/Learnbot_ico.png
learnblock-3.1.7.data/data/share/learnbot_dsl/mdfiles/styles.css
learnblock-3.1.7.data/data/share/learnbot_dsl/mdfiles/EN/1. Introduction/README.md
learnblock-3.1.7.data/data/share/learnbot_dsl/mdfiles/EN/2. Block programming/README.md
learnblock-3.1.7.data/data/share/learnbot_dsl/mdfiles/EN/3. Code generation/README.md
learnblock-3.1.7.data/data/share/learnbot_dsl/mdfiles/EN/4. Program execution/README.md
learnblock-3.1.7.data/data/share/learnbot_dsl/mdfiles/EN/5. Using LearnBlock with different robots/README.md
learnblock-3.1.7.data/data/share/learnbot_dsl/mdfiles/EN/5. Using LearnBlock with different robots/1. EBO/README.md
learnblock-3.1.7.data/data/share/learnbot_dsl/mdfiles/EN/5. Using LearnBlock with different robots/2. Cozmo/README.md
learnblock-3.1.7.data/data/share/learnbot_dsl/mdfiles/EN/5. Using LearnBlock with different robots/3. Thymio/README.md
learnblock-3.1.7.data/data/share/learnbot_dsl/mdfiles/EN/5. Using LearnBlock with different robots/4. EV3/README.md
learnblock-3.1.7.data/data/share/learnbot_dsl/mdfiles/EN/5. Using LearnBlock with different robots/5. Simulated EBO under RCIS/README.md
learnblock-3.1.7.data/data/share/learnbot_dsl/mdfiles/EN/5. Using LearnBlock with different robots/6. Simulated EV3 under V-REP/README.md
learnblock-3.1.7.data/data/share/learnbot_dsl/mdfiles/ES/1. Bienvenido a LearnBlock/README.md
learnblock-3.1.7.data/data/share/learnbot_dsl/mdfiles/ES/2. Programar con bloques en LearnBlock/README.md
learnblock-3.1.7.data/data/share/learnbot_dsl/mdfiles/ES/3. De bloques a texto/README.md
learnblock-3.1.7.data/data/share/learnbot_dsl/mdfiles/ES/4. Ejecutar un programa desde LearnBlock/README.md
learnblock-3.1.7.data/data/share/learnbot_dsl/mdfiles/ES/5. Uso de LearnBlock con diferentes robots/README.md
learnblock-3.1.7.dist-info/LICENSE
learnblock-3.1.7.dist-info/METADATA
learnblock-3.1.7.dist-info/WHEEL
learnblock-3.1.7.dist-info/top_level.txt
learnblock-3.1.7.dist-info/RECORD
