Metadata-Version: 2.1
Name: learnblock
Version: 3.1.7
Summary: Educational programming tool
Home-page: UNKNOWN
Author: Ivan Barbecho, Pilar Bachiller
Author-email: ivanbd@unex.es, pilarb@unex.es
License: GPL
Project-URL: Documentation, https://github.com/robocomp/LearnBlock/wiki
Project-URL: Funding, https://www.paypal.com/cgi-bin/webscr?cmd=_s-xclick&hosted_button_id=N3VAYG9VP8S4L
Project-URL: Source, https://github.com/robocomp/LearnBlock
Project-URL: Tracker, https://github.com/robocomp/LearnBlock/issues
Keywords: Visual programming learning robots
Platform: Posix
Platform: MacOS
Classifier: Development Status :: 5 - Production/Stable
Classifier: Intended Audience :: Education
Classifier: License :: OSI Approved :: GNU Lesser General Public License v3 (LGPLv3)
Classifier: Operating System :: MacOS :: MacOS X
Classifier: Operating System :: POSIX
Classifier: Operating System :: POSIX :: Linux
Classifier: Programming Language :: Python :: 3.4
Classifier: Programming Language :: Python :: 3.5
Classifier: Programming Language :: Python :: 3.6
Classifier: Programming Language :: Python :: 3.7
Classifier: Environment :: X11 Applications :: Qt
Requires-Dist: apriltag
Requires-Dist: requests (>=2.20.0)
Requires-Dist: pyunpack (>=0.1.2)
Requires-Dist: opencv-python-headless (>=3.4.3.18)
Requires-Dist: imutils (>=0.5.1)
Requires-Dist: six (>=1.10.0)
Requires-Dist: tensorflow (>=1.10.1)
Requires-Dist: dlib (>=19.13.1)
Requires-Dist: paramiko (>=2.4.2)
Requires-Dist: Pillow (>=5.3.0)
Requires-Dist: paho-mqtt (>=1.4.0)
Requires-Dist: PySide2
Requires-Dist: pyparsing (>=2.0.3)
Requires-Dist: qdarkstyle
Requires-Dist: future (>=0.16.0)
